jupyterlab_accessible_themes/__init__.py
jupyterlab_accessible_themes/_version.py
jupyterlab_accessible_themes/labextensions/githubdark/package.json
jupyterlab_accessible_themes/labextensions/githubdark/static/568.3cab7ae90a647c555c57.js
jupyterlab_accessible_themes/labextensions/githubdark/static/remoteEntry.c5de375f4fe1f2efcd26.js
jupyterlab_accessible_themes/labextensions/githubdark/static/style.js
jupyterlab_accessible_themes/labextensions/githubdark/static/third-party-licenses.json
jupyterlab_accessible_themes/labextensions/githubdark/themes/@jupyterlab-accessible-themes/jupyterlab-theme-githubdark/index.css
jupyterlab_accessible_themes/labextensions/githubdark/themes/@jupyterlab-accessible-themes/jupyterlab-theme-githubdark/index.js
jupyterlab_accessible_themes/labextensions/githublight/package.json
jupyterlab_accessible_themes/labextensions/githublight/static/568.5ce17d1cf09f489a6035.js
jupyterlab_accessible_themes/labextensions/githublight/static/remoteEntry.088be87b2ba77a6fe033.js
jupyterlab_accessible_themes/labextensions/githublight/static/style.js
jupyterlab_accessible_themes/labextensions/githublight/static/third-party-licenses.json
jupyterlab_accessible_themes/labextensions/githublight/themes/@jupyterlab-accessible-themes/jupyterlab-theme-githublight/index.css
jupyterlab_accessible_themes/labextensions/githublight/themes/@jupyterlab-accessible-themes/jupyterlab-theme-githublight/index.js
jupyterlab_accessible_themes/labextensions/pitayasmoothie/package.json
jupyterlab_accessible_themes/labextensions/pitayasmoothie/static/568.5f64d5f53fcb84ae256f.js
jupyterlab_accessible_themes/labextensions/pitayasmoothie/static/remoteEntry.4d84b866773f4b47b5ca.js
jupyterlab_accessible_themes/labextensions/pitayasmoothie/static/style.js
jupyterlab_accessible_themes/labextensions/pitayasmoothie/static/third-party-licenses.json
jupyterlab_accessible_themes/labextensions/pitayasmoothie/themes/@jupyterlab-accessible-themes/jupyterlab-theme-pitayasmoothie/index.css
jupyterlab_accessible_themes-0.2.0.dist-info/LICENSE
jupyterlab_accessible_themes-0.2.0.dist-info/METADATA
jupyterlab_accessible_themes-0.2.0.dist-info/WHEEL
jupyterlab_accessible_themes-0.2.0.dist-info/top_level.txt
jupyterlab_accessible_themes-0.2.0.dist-info/RECORD
