Metadata-Version: 2.1
Name: jupyterlab-accessible-themes
Version: 0.2.0
Summary: accessible jupyter lab themes
Home-page: https://github.com/github_username/jupyterlab-accessible-themes
Author: quansight-labs
Author-email: contact@quansight.com
License: BSD-3-Clause
Project-URL: Bug Tracker, https://github.com/github_username/jupyterlab-accessible-themes/issues
Project-URL: Source Code, https://github.com/Quansight-Labs/jupyterlab-accessible-themes
Requires-Python: >=3.8
License-File: LICENSE
